type/__init__.py
type/pid.py
type/primitive_u64.py
type/readable.py
type/rv_type.py
type/writable.py
nex_retendo-1.1.1.dist-info/LICENSE
nex_retendo-1.1.1.dist-info/METADATA
nex_retendo-1.1.1.dist-info/WHEEL
nex_retendo-1.1.1.dist-info/top_level.txt
nex_retendo-1.1.1.dist-info/RECORD
