Metadata-Version: 2.1
Name: nex_retendo
Version: 1.1.1
Summary: NEX Library of NEX Server for Wii U & 3DS.
Author: Retendo Contributors
Classifier: Programming Language :: Python :: 3
Classifier: License :: OSI Approved :: MIT License
Classifier: Operating System :: OS Independent
Requires-Python: >=3.6
License-File: LICENSE
Requires-Dist: grpcio-tools
